cloudshell/__init__.py
cloudshell/cp/__init__.py
cloudshell/cp/aws/__init__.py
cloudshell/cp/aws/aws_shell.py
cloudshell/cp/aws/common/__init__.py
cloudshell/cp/aws/common/cached_property.py
cloudshell/cp/aws/common/converters.py
cloudshell/cp/aws/common/deploy_data_holder.py
cloudshell/cp/aws/common/exceptions.py
cloudshell/cp/aws/common/retry_helper.py
cloudshell/cp/aws/common/role_for_instance.py
cloudshell/cp/aws/common/subnet_service.py
cloudshell/cp/aws/domain/__init__.py
cloudshell/cp/aws/domain/ami_management/__init__.py
cloudshell/cp/aws/domain/ami_management/operations/__init__.py
cloudshell/cp/aws/domain/ami_management/operations/access_key_operation.py
cloudshell/cp/aws/domain/ami_management/operations/delete_operation.py
cloudshell/cp/aws/domain/ami_management/operations/deploy_operation.py
cloudshell/cp/aws/domain/ami_management/operations/power_operation.py
cloudshell/cp/aws/domain/ami_management/operations/refresh_ip_operation.py
cloudshell/cp/aws/domain/ami_management/operations/snapshot_operation.py
cloudshell/cp/aws/domain/common/CheckCancellationThread.py
cloudshell/cp/aws/domain/common/__init__.py
cloudshell/cp/aws/domain/common/aws_session_manager.py
cloudshell/cp/aws/domain/common/cancellation_service.py
cloudshell/cp/aws/domain/common/exceptions.py
cloudshell/cp/aws/domain/common/list_helper.py
cloudshell/cp/aws/domain/common/vm_details_provider.py
cloudshell/cp/aws/domain/conncetivity/__init__.py
cloudshell/cp/aws/domain/conncetivity/operations/__init__.py
cloudshell/cp/aws/domain/conncetivity/operations/cleanup.py
cloudshell/cp/aws/domain/conncetivity/operations/prepare.py
cloudshell/cp/aws/domain/conncetivity/operations/prepare_subnet_executor.py
cloudshell/cp/aws/domain/conncetivity/operations/traffic_mirror_cleaner.py
cloudshell/cp/aws/domain/conncetivity/operations/traffic_mirroring_operation.py
cloudshell/cp/aws/domain/context/__init__.py
cloudshell/cp/aws/domain/context/aws_api.py
cloudshell_cp_aws-3.6.3.dist-info/METADATA
cloudshell_cp_aws-3.6.3.dist-info/WHEEL
cloudshell_cp_aws-3.6.3.dist-info/top_level.txt
cloudshell_cp_aws-3.6.3.dist-info/RECORD
