Metadata-Version: 2.1
Name: cloudshell-cp-aws
Version: 3.6.3
Summary: A repository for projects providing out of the box capabilities within CloudShell to define AWS instances in CloudShell and leverage Amazon Cloud Computing capabilities to deploy and connect apps in CloudShell sandboxes.
Home-page: http://www.qualisystems.com/
Author: QualiSystems
Author-email: info@qualisystems.com
Requires-Python: ~=3.7
Requires-Dist: setuptools >=40.0
Requires-Dist: cloudshell-automation-api >=9.3
Requires-Dist: cloudshell-shell-core ~=5.0
Requires-Dist: cloudshell-cp-core ~=1.2.0
Requires-Dist: boto3 ~=1.17
Requires-Dist: netaddr ==0.7.19
Requires-Dist: jsonpickle ~=1.0
Requires-Dist: retrying ~=1.3.3
Requires-Dist: jsonschema ~=3.2
Requires-Dist: cryptography ~=3.2.0
Requires-Dist: attrs ~=21.2
Requires-Dist: typing-extensions ~=3.0
